mcp_server_secops/__init__.py
mcp_server_secops/__main__.py
mcp_server_secops/server.py
mcp_server_secops/tools/amass.py
mcp_server_secops/tools/dirsearch.py
mcp_server_secops/tools/ffuf.py
mcp_server_secops/tools/hashcat.py
mcp_server_secops/tools/httpx.py
mcp_server_secops/tools/ipinfo.py
mcp_server_secops/tools/nmap.py
mcp_server_secops/tools/nuclei.py
mcp_server_secops/tools/sqlmap.py
mcp_server_secops/tools/subfinder.py
mcp_server_secops/tools/tlsx.py
mcp_server_secops/tools/wfuzz.py
mcp_server_secops/tools/xsstrike.py
mcp_server_secops-0.1.0.dist-info/METADATA
mcp_server_secops-0.1.0.dist-info/WHEEL
mcp_server_secops-0.1.0.dist-info/entry_points.txt
mcp_server_secops-0.1.0.dist-info/RECORD
