Metadata-Version: 2.4
Name: mcp-server-secops
Version: 0.1.0
Summary: Servidor MCP con herramientas de pentesting integradas
Requires-Python: >=3.10
Requires-Dist: aiohttp
Requires-Dist: beautifulsoup4
Requires-Dist: fastapi
Requires-Dist: lxml
Requires-Dist: mcp[cli]>=1.9.0
Requires-Dist: pydantic
Requires-Dist: python-dotenv
Requires-Dist: requests
Requires-Dist: uvicorn
